tpmstream/__init__.py
tpmstream/__main__.py
tpmstream/get_cmds.py
tpmstream/common/__init__.py
tpmstream/common/canonical.py
tpmstream/common/constraints.py
tpmstream/common/error.py
tpmstream/common/event.py
tpmstream/common/object.py
tpmstream/common/path.py
tpmstream/common/util.py
tpmstream/data/__init__.py
tpmstream/data/dlopen-esys-get-random.int.pcap
tpmstream/data/esys-act-set-timeout.int.pcap
tpmstream/data/esys-audit.int.pcap
tpmstream/data/esys-auto-session-flags.int.pcap
tpmstream/data/esys-certify-creation.int.pcap
tpmstream/data/esys-certify.int.pcap
tpmstream/data/esys-certifyX509.int.pcap
tpmstream/data/esys-change-eps.int.pcap
tpmstream/data/esys-clear-control.int.pcap
tpmstream/data/esys-clear-session.int.pcap
tpmstream/data/esys-clear.int.pcap
tpmstream/data/esys-clockset-audit.int.pcap
tpmstream/data/esys-clockset.int.pcap
tpmstream/data/esys-commit.int.pcap
tpmstream/data/esys-create-fail.int.pcap
tpmstream/data/esys-create-password-auth.int.pcap
tpmstream/data/esys-create-policy-auth.int.pcap
tpmstream/data/esys-create-primary-ecc-hmac.int.pcap
tpmstream/data/esys-create-primary-hmac.int.pcap
tpmstream/data/esys-create-session-auth-bound.int.pcap
tpmstream/data/esys-create-session-auth-ecc.int.pcap
tpmstream/data/esys-create-session-auth-long.int.pcap
tpmstream/data/esys-create-session-auth-xor.int.pcap
tpmstream/data/esys-create-session-auth.int.pcap
tpmstream/data/esys-create-session-null-bind-no-tpm-key.int.pcap
tpmstream/data/esys-create-session-null-bind-tpm-key.int.pcap
tpmstream/data/esys-createloaded-session.int.pcap
tpmstream/data/esys-createloaded.int.pcap
tpmstream/data/esys-duplicate.int.pcap
tpmstream/data/esys-ecc-parameters.int.pcap
tpmstream/data/esys-ecdh-keygen.int.pcap
tpmstream/data/esys-ecdh-zgen.int.pcap
tpmstream/data/esys-encrypt-decrypt.int.pcap
tpmstream/data/esys-encrypt-decrypt2.int.pcap
tpmstream/data/esys-event-sequence-complete.int.pcap
tpmstream/data/esys-evict-control-serialization.int.pcap
tpmstream-0.1.10.dist-info/LICENSE
tpmstream-0.1.10.dist-info/METADATA
tpmstream-0.1.10.dist-info/WHEEL
tpmstream-0.1.10.dist-info/entry_points.txt
tpmstream-0.1.10.dist-info/top_level.txt
tpmstream-0.1.10.dist-info/RECORD
